{
  "crochet": {
    "cached_at": "2026-05-03T02:01:31+00:00",
    "report": {
      "keyword": "crochet",
      "bucket": "spike",
      "opportunity_score": 57.5,
      "competition": "high",
      "action": "competitive",
      "trend": "rising",
      "trend_strength": 0.422,
      "revenue_change_pct": -91.75,
      "price_range": "5-20",
      "total_listings": 2720,
      "demand_supply_ratio": 0.13,
      "error": "",
      "action_reason_en": "Decent market but crowded — need strong differentiation",
      "top_shop_id": 32081894,
      "top_shop_country": "US",
      "top_shop_revenue_usd": 57327.26,
      "top_shop_listings": 7,
      "top_shop_sample_listing_id": 0,
      "top_listing_id": 4464104825,
      "top_listing_title": "Popcorn Bucket Blanket Crochet Pattern PDF | Movie Night Basket + Matching Throw Blanket",
      "top_listing_price_usd": 5.8,
      "top_listing_total_sold": 54,
      "top_listing_revenue_usd": 313.2
    }
  }
}